felucca/__init__.py
felucca/backend/protostar.py
felucca/backend/python_package.py
felucca/core/enums.py
felucca/core/utils.py
felucca/main.py
felucca-0.2.5.dist-info/entry_points.txt
felucca-0.2.5.dist-info/METADATA
felucca-0.2.5.dist-info/WHEEL
felucca-0.2.5.dist-info/RECORD
