Metadata-Version: 2.1
Name: felucca
Version: 0.2.5
Summary: Cairo dependency management and packaging made easy.
License: MIT
Keywords: packaging,dependency,poetry
Author: Fran Algaba
Author-email: f.algaba.work@gmail.com
Requires-Python: >=3.9,<3.10
Classifier: License :: OSI Approved :: MIT License
Classifier: Programming Language :: Python :: 3
Classifier: Programming Language :: Python :: 3.9
Classifier: Topic :: Software Development :: Build Tools
Classifier: Topic :: Software Development :: Libraries :: Python Modules
Requires-Dist: GitPython (>=3.1.30,<4.0.0)
Requires-Dist: click (==8.0.4)
Requires-Dist: cookiecutter (>=1.7.3,<2.0.0)
Requires-Dist: requests (>=2.27.1,<3.0.0)
Requires-Dist: rich (>=12.0.1,<13.0.0)
Requires-Dist: toml (>=0.10.2,<0.11.0)
Requires-Dist: typer (>=0.4.1,<0.5.0)
